brahe-1.0.1.dist-info/METADATA
brahe-1.0.1.dist-info/WHEEL
brahe-1.0.1.dist-info/entry_points.txt
brahe-1.0.1.dist-info/licenses/LICENSE.md
brahe/__init__.py
brahe/_brahe.cp310-win_amd64.pyd
brahe/access.py
brahe/attitude.py
brahe/brahe.pyi
brahe/cli/__init__.py
brahe/cli/__main__.py
brahe/cli/access.py
brahe/cli/datasets/__init__.py
brahe/cli/datasets/celestrak.py
brahe/cli/datasets/groundstations.py
brahe/cli/eop.py
brahe/cli/orbits.py
brahe/cli/time.py
brahe/cli/transform.py
brahe/cli/utils.py
brahe/constants.py
brahe/coordinates.py
brahe/datasets.py
brahe/eop.py
brahe/events.py
brahe/frames.py
brahe/integrators.py
brahe/logging.py
brahe/math.py
brahe/orbit_dynamics.py
brahe/orbits.py
brahe/plots/__init__.py
brahe/plots/access_geometry.py
brahe/plots/backend.py
brahe/plots/basemap.py
brahe/plots/gabbard.py
brahe/plots/groundtrack.py
brahe/plots/texture_utils.py
brahe/plots/trajectories.py
brahe/plots/trajectory_3d.py
brahe/propagators.py
brahe/py.typed
brahe/relative_motion.py
brahe/space_weather.py
brahe/time.py
brahe/trajectories.py
brahe/utils.py
brahe-1.0.1.dist-info/RECORD
