Metadata-Version: 2.4
Name: brahe
Version: 1.0.1
Classifier: Development Status :: 4 - Beta
Classifier: Intended Audience :: Science/Research
Classifier: License :: OSI Approved :: MIT License
Classifier: Operating System :: Microsoft :: Windows
Classifier: Operating System :: MacOS :: MacOS X
Classifier: Operating System :: POSIX :: Linux
Classifier: Programming Language :: Python :: 3
Classifier: Programming Language :: Python :: 3.10
Classifier: Programming Language :: Python :: 3.11
Classifier: Programming Language :: Python :: 3.12
Classifier: Programming Language :: Python :: 3.13
Classifier: Programming Language :: Python :: 3.14
Requires-Dist: numpy>=2.0.0
Requires-Dist: rich>=14.0.0
Requires-Dist: typer>=0.16.0
Requires-Dist: matplotlib>=3.9.4
Requires-Dist: plotly>=6.0.0
Requires-Dist: cartopy>=0.23.0
Requires-Dist: shapely>=2.0.0
Requires-Dist: pillow>=10.0.0
Requires-Dist: httpx>=0.27.0
Requires-Dist: kaleido>=0.2.0
Requires-Dist: loguru>=0.7.0
Requires-Dist: scienceplots>=2.0.0 ; extra == 'plots'
Requires-Dist: brahe[plots] ; extra == 'all'
Provides-Extra: plots
Provides-Extra: all
License-File: LICENSE.md
Summary: Brahe is a modern satellite dynamics library for research and engineering applications designed to be easy-to-learn, high-performance, and quick-to-deploy. The north-star of the development is enabling users to solve meaningful problems and answer questions quickly, easily, and correctly.
Keywords: space,astrodynamics,satellite,research
Home-Page: https://duncaneddy.github.io/brahe/
Author-email: Duncan Eddy <duncan.eddy@gmail.com>
Maintainer-email: Duncan Eddy <duncan.eddy@gmail.com>
Requires-Python: >=3.10
Project-URL: Documentation, https://duncaneddy.github.io/brahe/
Project-URL: Repository, https://github.com/duncaneddy/brahe
Project-URL: Issues, https://github.com/duncaneddy/brahe/pulls
